{
  "alerts": [
    {
      "id": "alrt_0001",
      "severity": "sev3",
      "status": "resolved",
      "demo": "tax-assessment",
      "monitor_id": "mon_tax-assessment_0002",
      "triggered_at": "2026-05-15T09:56:53+00:00",
      "resolved_at": "2026-05-15T17:42:53+00:00",
      "title": "Volume check failed on marts.fct_assessments",
      "detail": "Threshold: row-count \u00b12% vs 7d avg \u00b7 Observed: 5.2% \u0394",
      "owner": "@chletsos",
      "runbook_url": "https://runbooks.fivetran-internal.example/volume"
    },
    {
      "id": "alrt_0002",
      "severity": "sev3",
      "status": "active",
      "demo": "tax-assessment",
      "monitor_id": "mon_tax-assessment_0012",
      "triggered_at": "2026-05-14T13:58:53+00:00",
      "resolved_at": null,
      "title": "Distribution check failed on marts.dim_parcel",
      "detail": "Threshold: mean within \u00b13\u03c3 \u00b7 Observed: 5.1\u03c3 from baseline",
      "owner": "@chletsos",
      "runbook_url": "https://runbooks.fivetran-internal.example/distribution"
    },
    {
      "id": "alrt_0003",
      "severity": "sev3",
      "status": "active",
      "demo": "healthcare",
      "monitor_id": "mon_healthcare_0039",
      "triggered_at": "2026-05-15T17:19:53+00:00",
      "resolved_at": null,
      "title": "Referential check failed on marts.fct_encounter",
      "detail": "Threshold: FK reference integrity \u2265 2% \u00b7 Observed: 2.5% orphans",
      "owner": "@clinical-data",
      "runbook_url": "https://runbooks.fivetran-internal.example/referential"
    },
    {
      "id": "alrt_0004",
      "severity": "sev1",
      "status": "acknowledged",
      "demo": "finserv",
      "monitor_id": "mon_finserv_0077",
      "triggered_at": "2026-05-15T09:29:53+00:00",
      "resolved_at": null,
      "title": "Nulls check failed on marts.dim_issuer",
      "detail": "Threshold: null rate \u2264 2% \u00b7 Observed: 4.8% null",
      "owner": "@research",
      "runbook_url": "https://runbooks.fivetran-internal.example/nulls"
    },
    {
      "id": "alrt_0005",
      "severity": "sev3",
      "status": "resolved",
      "demo": "finserv",
      "monitor_id": "mon_finserv_0087",
      "triggered_at": "2026-05-15T00:07:53+00:00",
      "resolved_at": "2026-05-15T17:30:53+00:00",
      "title": "Referential check failed on marts.fct_macro_series",
      "detail": "Threshold: FK reference integrity \u2265 5% \u00b7 Observed: 6.4% orphans",
      "owner": "@research",
      "runbook_url": "https://runbooks.fivetran-internal.example/referential"
    },
    {
      "id": "alrt_0006",
      "severity": "sev2",
      "status": "active",
      "demo": "finserv",
      "monitor_id": "mon_finserv_0096",
      "triggered_at": "2026-05-14T16:27:53+00:00",
      "resolved_at": null,
      "title": "Custom_Sql check failed on marts.fct_complaints",
      "detail": "Threshold: row count > 2 \u00b7 Observed: found 3.7",
      "owner": "@research",
      "runbook_url": "https://runbooks.fivetran-internal.example/custom_sql"
    },
    {
      "id": "alrt_0007",
      "severity": "sev3",
      "status": "active",
      "demo": "retail",
      "monitor_id": "mon_retail_0147",
      "triggered_at": "2026-05-15T09:29:53+00:00",
      "resolved_at": null,
      "title": "Schema check failed on marts.fct_carts",
      "detail": "Threshold: no breaking schema change \u00b7 Observed: 9.5 new column(s)",
      "owner": "@ecom",
      "runbook_url": "https://runbooks.fivetran-internal.example/schema"
    },
    {
      "id": "alrt_0008",
      "severity": "sev3",
      "status": "active",
      "demo": "retail",
      "monitor_id": "mon_retail_0149",
      "triggered_at": "2026-05-14T16:31:53+00:00",
      "resolved_at": null,
      "title": "Nulls check failed on marts.fct_carts",
      "detail": "Threshold: null rate \u2264 10% \u00b7 Observed: 17.9% null",
      "owner": "@ecom",
      "runbook_url": "https://runbooks.fivetran-internal.example/nulls"
    },
    {
      "id": "alrt_0009",
      "severity": "sev1",
      "status": "acknowledged",
      "demo": "retail",
      "monitor_id": "mon_retail_0156",
      "triggered_at": "2026-05-14T13:08:53+00:00",
      "resolved_at": null,
      "title": "Distribution check failed on marts.dim_customer",
      "detail": "Threshold: mean within \u00b13\u03c3 \u00b7 Observed: 8.6\u03c3 from baseline",
      "owner": "@ecom",
      "runbook_url": "https://runbooks.fivetran-internal.example/distribution"
    },
    {
      "id": "alrt_0010",
      "severity": "sev3",
      "status": "active",
      "demo": "lifesci",
      "monitor_id": "mon_lifesci_0244",
      "triggered_at": "2026-05-15T00:20:53+00:00",
      "resolved_at": null,
      "title": "Distribution check failed on marts.fct_adverse_event",
      "detail": "Threshold: mean within \u00b110\u03c3 \u00b7 Observed: 17.0\u03c3 from baseline",
      "owner": "@biostats",
      "runbook_url": "https://runbooks.fivetran-internal.example/distribution"
    },
    {
      "id": "alrt_0011",
      "severity": "sev2",
      "status": "active",
      "demo": "tax-assessment",
      "triggered_at": "2026-05-15T15:08:53+00:00",
      "resolved_at": null,
      "title": "Connector wprdc \u2192 databricks degraded",
      "detail": "Lag 120s \u00b7 throughput dropped to 538/s",
      "owner": "@chletsos"
    },
    {
      "id": "alrt_0012",
      "severity": "sev2",
      "status": "active",
      "demo": "finserv",
      "triggered_at": "2026-05-15T17:25:53+00:00",
      "resolved_at": null,
      "title": "Connector cfpb \u2192 athena/iceberg degraded",
      "detail": "Lag 384s \u00b7 throughput dropped to 4954/s",
      "owner": "@research"
    },
    {
      "id": "alrt_0013",
      "severity": "sev1",
      "status": "active",
      "demo": "retail",
      "triggered_at": "2026-05-15T17:56:53+00:00",
      "resolved_at": null,
      "title": "Connector shopify \u2192 athena/iceberg failing",
      "detail": "Lag 9400s \u00b7 throughput dropped to 0/s",
      "owner": "@ecom"
    },
    {
      "id": "alrt_0014",
      "severity": "sev1",
      "status": "active",
      "demo": "techsaas",
      "triggered_at": "2026-05-15T16:42:53+00:00",
      "resolved_at": null,
      "title": "Connector salesforce \u2192 athena/iceberg failing",
      "detail": "Lag 3000s \u00b7 throughput dropped to 0/s",
      "owner": "@platform"
    },
    {
      "id": "alrt_0015",
      "severity": "sev2",
      "status": "active",
      "demo": "techsaas",
      "triggered_at": "2026-05-15T15:36:53+00:00",
      "resolved_at": null,
      "title": "Connector stripe \u2192 athena/iceberg degraded",
      "detail": "Lag 72s \u00b7 throughput dropped to 1142/s",
      "owner": "@platform"
    }
  ]
}